README.txt
setup.py
mrgit/__init__.py
mrgit.web.egg-info/PKG-INFO
mrgit.web.egg-info/SOURCES.txt
mrgit.web.egg-info/dependency_links.txt
mrgit.web.egg-info/entry_points.txt
mrgit.web.egg-info/namespace_packages.txt
mrgit.web.egg-info/not-zip-safe
mrgit.web.egg-info/paster_plugins.txt
mrgit.web.egg-info/requires.txt
mrgit.web.egg-info/top_level.txt
mrgit/web/__init__.py
mrgit/web/app.py
mrgit/web/models.py
mrgit/web/views.py