Metadata-Version: 1.0
Name: mrgit.web
Version: 0.1
Summary: mrgit.web
Home-page: http://code.garbas.si/mrgit.web
Author: Rok Garbas
Author-email: rok@garbas.si
License: UNKNOWN
Keywords: web wsgi repoze bfg zope git gitweb
Platform: UNKNOWN
Classifier: Development Status :: 3 - Alpha
Classifier: Intended Audience :: Developers
Classifier: Programming Language :: Python
Classifier: Topic :: Internet :: WWW/HTTP
Classifier: Topic :: Internet :: WWW/HTTP :: Dynamic Content
Classifier: Topic :: Internet :: WWW/HTTP :: WSGI
Classifier: Topic :: Internet :: WWW/HTTP :: WSGI :: Application
